{
  "Cr0" : 0.002,

  "CBf"  : 6300.0,
  "CBr"  : 4800.0,

  "h_RRC" : 0.08,
  "Kr_eq" : 0.2283,
  "q" : 0.2187,

  "Cx" : 1.2,
  "Cz": 3.49,
  "rho": 1.2,
  "S": 1.0,
  "aero_split_front": 0.413,
  
  "steer_ratio" : 15.0,

  "By_f"   : -17.96,
  "Cy_f"   : 1.35,
  "Dy_f"   : 1.38,
  "Ey_f"   : 0.0,
  "Svy_f"  : 0.0,
  "Shy_f"  : 0.0,
  
  "By_r"   : -17.0,
  "Cy_r"   : 1.399,
  "Dy_r"   : 1.8,
  "Ey_r"   : -3.568,
  "Svy_r"  : 0.0,
  "Shy_r"  : 0.0,

  "Dx_f" : 1.4,
  "Dx_r" : 1.4,
  "Bx" : 24.0,
  "Cx" : 1.6,
  "Svx" : -0.03,

  "m"     : 567.0,
  "Iz"    : 500.0,
  "lf"    : 1.652,
  "lr"    : 1.148,
  "L"     : 2.8,
  "tr"    : 1.5105,
  "h"     : 0.28,

  "J_eng" : 1.8,
  "J_0"   : 5.45,
  "preload" : 0.0,
  "locking" : 30.0,

  "car_l": 2.5,
  "car_w": 0.9,

  "g"   : 9.81,
  
  "Eps_f" : 1.0,
  "Eps_r" : 1.0,
  "E_long" : 1.0,
  "E_lat" : 1.0,
  "E_eps" : 1.0,

  "vx_zero": 0.1,

  "final_ratio": 2.833,
  "wh_radius": 0.2606,
  "gear_ratio": [2.75, 2.07, 1.667, 1.37, 1.17, 1.0],
  "motor_model_vx": [18.9, 38.3, 51.9, 64.4, 74.7, 86.9],
  "rpm_idle": 1000.0,
  "rpm_limiter": 7000,
  "eta_engine": 1.0,

  "vx_kin_dyn_blend": 2.0,
  "kin_dyn_blend_smoothing": 3.0,

  "RADS_2_RPM" : 9.5493

}